LICENSE
requirements-dev.txt
requirements.txt
text2vec/__init__.py
text2vec/similarity.py
text2vec/vector.py
text2vec/version.py
text2vec/algorithm/__init__.py
text2vec/algorithm/distance.py
text2vec/algorithm/rank_bm25.py
text2vec/bert/__init__.py
text2vec/bert/extract_feature.py
text2vec/bert/graph.py
text2vec/bert/model.py
text2vec/bert/modeling.py
text2vec/bert/optimization.py
text2vec/bert/predict.py
text2vec/bert/tokenization.py
text2vec/bert/train.py
text2vec/embeddings/__init__.py
text2vec/embeddings/bert_embedding.py
text2vec/embeddings/embedding.py
text2vec/embeddings/word_embedding.py
text2vec/processors/__init__.py
text2vec/processors/base_processor.py
text2vec/processors/default_processor.py
text2vec/utils/__init__.py
text2vec/utils/get_file.py
text2vec/utils/logger.py
text2vec/utils/ngram.py
text2vec/utils/non_masking_layer.py
text2vec/utils/timer.py
text2vec/utils/tokenizer.py
whjtext2vec/__init__.py
whjtext2vec/similarity.py
whjtext2vec/vector.py
whjtext2vec/version.py
whjtext2vec/algorithm/__init__.py
whjtext2vec/algorithm/distance.py
whjtext2vec/algorithm/rank_bm25.py
whjtext2vec/bert/__init__.py
whjtext2vec/bert/extract_feature.py
whjtext2vec/bert/graph.py
whjtext2vec/bert/model.py
whjtext2vec/bert/modeling.py
whjtext2vec/bert/optimization.py
whjtext2vec/bert/predict.py
whjtext2vec/bert/tokenization.py
whjtext2vec/bert/train.py
whjtext2vec/embeddings/__init__.py
whjtext2vec/embeddings/bert_embedding.py
whjtext2vec/embeddings/embedding.py
whjtext2vec/embeddings/word_embedding.py
whjtext2vec/processors/__init__.py
whjtext2vec/processors/base_processor.py
whjtext2vec/processors/default_processor.py
whjtext2vec/utils/__init__.py
whjtext2vec/utils/get_file.py
whjtext2vec/utils/logger.py
whjtext2vec/utils/ngram.py
whjtext2vec/utils/non_masking_layer.py
whjtext2vec/utils/timer.py
whjtext2vec/utils/tokenizer.py
whjtext2vec-0.1.4.dist-info/LICENSE
whjtext2vec-0.1.4.dist-info/METADATA
whjtext2vec-0.1.4.dist-info/WHEEL
whjtext2vec-0.1.4.dist-info/top_level.txt
whjtext2vec-0.1.4.dist-info/RECORD
